LICENSE
MANIFEST.in
README.rst
setup.py
django_tethys_wps.egg-info/PKG-INFO
django_tethys_wps.egg-info/SOURCES.txt
django_tethys_wps.egg-info/dependency_links.txt
django_tethys_wps.egg-info/requires.txt
django_tethys_wps.egg-info/top_level.txt
tethys_wps/__init__.py
tethys_wps/admin.py
tethys_wps/apps.py
tethys_wps/base.py
tethys_wps/models.py
tethys_wps/urls.py
tethys_wps/utilities.py
tethys_wps/views.py
tethys_wps/static/tethys_wps/css/tethys_wps.css
tethys_wps/static/tethys_wps/js/tethys_wps.js
tethys_wps/templates/tethys_wps/base.html
tethys_wps/templates/tethys_wps/home.html
tethys_wps/templates/tethys_wps/process.html
tethys_wps/templates/tethys_wps/service.html
tethys_wps/templatetags/__init__.py
tethys_wps/templatetags/tethys_wps.py